karabingen/__init__.py
karabingen/cli.py
scripts/tmb.sh
scripts/tmuxjump.py
karabingen-0.1.1.dist-info/METADATA
karabingen-0.1.1.dist-info/WHEEL
karabingen-0.1.1.dist-info/entry_points.txt
karabingen-0.1.1.dist-info/RECORD
