Metadata-Version: 2.4
Name: karabingen
Version: 0.1.1
Summary: CLI tool to generate Karabiner configuration
Author-email: fgazat <fgazat@yandex.ru>
Requires-Dist: pydantic>=2.0.0
Requires-Dist: pyyaml
